hawkflowclient/__init__.py
hawkflowclient/_endpoints.py
hawkflowclient/_hawkflow_exceptions.py
hawkflowclient/_validation.py
hawkflowclient/hawkflow_api.py
hawkflowclient/hawkflow_decorators.py
hawkflowclient/heart_beat.py
hawkflowclient/tests/__init__.py
hawkflowclient/tests/test_validation.py
hawkflow-0.0.9953.dist-info/LICENSE
hawkflow-0.0.9953.dist-info/METADATA
hawkflow-0.0.9953.dist-info/WHEEL
hawkflow-0.0.9953.dist-info/top_level.txt
hawkflow-0.0.9953.dist-info/RECORD
