Metadata-Version: 2.1
Name: hawkflow
Version: 0.0.9953
Summary: HawkFlow.ai
License: LICENSE
Project-URL: Homepage, https://github.com/hawkflow/hawkflow-py
Keywords: hawkflow,hawkflowclient,monitoring
Classifier: Development Status :: 5 - Production/Stable
Classifier: Programming Language :: Python :: 3.7
Classifier: Programming Language :: Python :: 3.8
Classifier: Programming Language :: Python :: 3.9
Classifier: Programming Language :: Python :: 3.10
Classifier: Programming Language :: Python :: 3.11
Classifier: License :: OSI Approved :: MIT License
Classifier: Operating System :: OS Independent
Requires-Python: >=3.7
License-File: LICENSE
Requires-Dist: requests >=2.25.1
